{ "program": { "name": "", "nodes": { "Start": { "name": "Start", "headers": [ { "key": "title", "value": "Start" } ], "instructions": [ { "runCommand": { "commandText": "bgm play title loop", "substitutionCount": 0 } }, { "runCommand": { "commandText": "bg title fade 0.5", "substitutionCount": 0 } }, { "runLine": { "lineID": "line:1eeaf1bf", "substitutionCount": 0 } }, { "runCommand": { "commandText": "wait 0.8", "substitutionCount": 0 } }, { "addOption": { "lineID": "line:88daf6c8", "destination": 10, "substitutionCount": 0, "hasCondition": false } }, { "addOption": { "lineID": "line:328bff51", "destination": 14, "substitutionCount": 0, "hasCondition": false } }, { "showOptions": { } }, { "jumpIfFalse": { "destination": 26 } }, { "pop": { } }, { "peekAndJump": { } }, { "pop": { } }, { "runCommand": { "commandText": "bgm fade 0.5", "substitutionCount": 0 } }, { "runNode": { "nodeName": "Intro" } }, { "jumpTo": { "destination": 26 } }, { "pop": { } }, { "runCommand": { "commandText": "load 1", "substitutionCount": 0 } }, { "pushVariable": { "variableName": "$_load_failed" } }, { "jumpIfFalse": { "destination": 24 } }, { "runLine": { "lineID": "line:a4bbf826", "substitutionCount": 0 } }, { "pushBool": { "value": false } }, { "storeVariable": { "variableName": "$_load_failed" } }, { "pop": { } }, { "runNode": { "nodeName": "Start" } }, { "jumpTo": { "destination": 25 } }, { "pop": { } }, { "jumpTo": { "destination": 26 } }, { "return": { } } ] }, "Intro": { "name": "Intro", "headers": [ { "key": "title", "value": "Intro" } ], "instructions": [ { "runCommand": { "commandText": "bg dungeon fade 0.3", "substitutionCount": 0 } }, { "runCommand": { "commandText": "sprite show ou center", "substitutionCount": 0 } }, { "runCommand": { "commandText": "bgm play dungeon loop", "substitutionCount": 0 } }, { "runLine": { "lineID": "line:eeec70fe", "substitutionCount": 0 } }, { "runLine": { "lineID": "line:78dc7789", "substitutionCount": 0 } }, { "addOption": { "lineID": "line:c28d7e10", "destination": 11, "substitutionCount": 0, "hasCondition": false } }, { "addOption": { "lineID": "line:54bd7967", "destination": 16, "substitutionCount": 0, "hasCondition": false } }, { "showOptions": { } }, { "jumpIfFalse": { "destination": 21 } }, { "pop": { } }, { "peekAndJump": { } }, { "pop": { } }, { "pushString": { "value": "アレフ" } }, { "storeVariable": { "variableName": "$player_name" } }, { "pop": { } }, { "jumpTo": { "destination": 21 } }, { "pop": { } }, { "pushString": { "value": "ベータ" } }, { "storeVariable": { "variableName": "$player_name" } }, { "pop": { } }, { "jumpTo": { "destination": 21 } }, { "pushVariable": { "variableName": "$player_name" } }, { "runLine": { "lineID": "line:c5a0c6f7", "substitutionCount": 1 } }, { "runLine": { "lineID": "line:5390c180", "substitutionCount": 0 } }, { "addOption": { "lineID": "line:f794e0ce", "destination": 30, "substitutionCount": 0, "hasCondition": false } }, { "addOption": { "lineID": "line:dbf5ee20", "destination": 36, "substitutionCount": 0, "hasCondition": false } }, { "showOptions": { } }, { "jumpIfFalse": { "destination": 42 } }, { "pop": { } }, { "peekAndJump": { } }, { "pop": { } }, { "pushBool": { "value": true } }, { "storeVariable": { "variableName": "$brave" } }, { "pop": { } }, { "runLine": { "lineID": "line:61a4e7b9", "substitutionCount": 0 } }, { "jumpTo": { "destination": 42 } }, { "pop": { } }, { "pushBool": { "value": false } }, { "storeVariable": { "variableName": "$brave" } }, { "pop": { } }, { "runLine": { "lineID": "line:4dc5e957", "substitutionCount": 0 } }, { "jumpTo": { "destination": 42 } }, { "runCommand": { "commandText": "sprite hide ou", "substitutionCount": 0 } }, { "runCommand": { "commandText": "wait 0.3", "substitutionCount": 0 } }, { "runNode": { "nodeName": "Room1" } }, { "return": { } } ] }, "Room1": { "name": "Room1", "headers": [ { "key": "title", "value": "Room1" }, { "key": "$Yarn.Internal.TrackingVariable", "value": "$Yarn.Internal.Visiting.Room1" } ], "instructions": [ { "runCommand": { "commandText": "bg room1 fade 0.5", "substitutionCount": 0 } }, { "runCommand": { "commandText": "bgm play room loop", "substitutionCount": 0 } }, { "runCommand": { "commandText": "hotspot unlock chest", "substitutionCount": 0 } }, { "runCommand": { "commandText": "hotspot unlock door", "substitutionCount": 0 } }, { "runLine": { "lineID": "line:9fa9601e", "substitutionCount": 0 } }, { "runLine": { "lineID": "line:09996769", "substitutionCount": 0 } }, { "pushString": { "value": "Room1" } }, { "pushFloat": { "value": 1 } }, { "callFunc": { "functionName": "visited_count" } }, { "pushFloat": { "value": 1 } }, { "pushFloat": { "value": 2 } }, { "callFunc": { "functionName": "Number.EqualTo" } }, { "jumpIfFalse": { "destination": 16 } }, { "pushVariable": { "variableName": "$player_name" } }, { "runLine": { "lineID": "line:b3c86ef0", "substitutionCount": 1 } }, { "jumpTo": { "destination": 19 } }, { "pop": { } }, { "runLine": { "lineID": "line:25f86987", "substitutionCount": 0 } }, { "jumpTo": { "destination": 19 } }, { "addOption": { "lineID": "line:b4e5d617", "destination": 27, "substitutionCount": 0, "hasCondition": false } }, { "addOption": { "lineID": "line:22d5d160", "destination": 30, "substitutionCount": 0, "hasCondition": false } }, { "addOption": { "lineID": "line:453e2032", "destination": 33, "substitutionCount": 0, "hasCondition": false } }, { "addOption": { "lineID": "line:695f2edc", "destination": 55, "substitutionCount": 0, "hasCondition": false } }, { "showOptions": { } }, { "jumpIfFalse": { "destination": 58 } }, { "pop": { } }, { "peekAndJump": { } }, { "pop": { } }, { "runNode": { "nodeName": "ChestNode" } }, { "jumpTo": { "destination": 58 } }, { "pop": { } }, { "runNode": { "nodeName": "DoorNode" } }, { "jumpTo": { "destination": 58 } }, { "pop": { } }, { "runCommand": { "commandText": "bg room fade 0.5", "substitutionCount": 0 } }, { "pushVariable": { "variableName": "$hp" } }, { "pushFloat": { "value": 10 } }, { "pushFloat": { "value": 2 } }, { "callFunc": { "functionName": "Number.Add" } }, { "storeVariable": { "variableName": "$hp" } }, { "pop": { } }, { "pushVariable": { "variableName": "$hp" } }, { "pushVariable": { "variableName": "$max_hp" } }, { "pushFloat": { "value": 2 } }, { "callFunc": { "functionName": "Number.GreaterThan" } }, { "jumpIfFalse": { "destination": 50 } }, { "pushVariable": { "variableName": "$max_hp" } }, { "storeVariable": { "variableName": "$hp" } }, { "pop": { } }, { "jumpTo": { "destination": 51 } }, { "pop": { } }, { "pushVariable": { "variableName": "$hp" } }, { "runLine": { "lineID": "line:d30e2745", "substitutionCount": 1 } }, { "runNode": { "nodeName": "Room1" } }, { "jumpTo": { "destination": 58 } }, { "pop": { } }, { "runNode": { "nodeName": "MeetKing" } }, { "jumpTo": { "destination": 58 } }, { "return": { } } ] }, "ChestNode": { "name": "ChestNode", "headers": [ { "key": "title", "value": "ChestNode" } ], "instructions": [ { "pushVariable": { "variableName": "$chest_opened" } }, { "jumpIfFalse": { "destination": 5 } }, { "runCommand": { "commandText": "sprite show chest open", "substitutionCount": 0 } }, { "runLine": { "lineID": "line:d8f0fbf7", "substitutionCount": 0 } }, { "jumpTo": { "destination": 20 } }, { "pop": { } }, { "runCommand": { "commandText": "sprite show chest closed", "substitutionCount": 0 } }, { "runCommand": { "commandText": "se chest_open", "substitutionCount": 0 } }, { "runCommand": { "commandText": "wait 0.4", "substitutionCount": 0 } }, { "runCommand": { "commandText": "sprite show chest open", "substitutionCount": 0 } }, { "runLine": { "lineID": "line:7b659f69", "substitutionCount": 0 } }, { "pushBool": { "value": true } }, { "storeVariable": { "variableName": "$chest_opened" } }, { "pop": { } }, { "runCommand": { "commandText": "item add key", "substitutionCount": 0 } }, { "pushBool": { "value": true } }, { "storeVariable": { "variableName": "$inv_key" } }, { "pop": { } }, { "runLine": { "lineID": "line:ed55981e", "substitutionCount": 0 } }, { "jumpTo": { "destination": 20 } }, { "runCommand": { "commandText": "sprite hide chest", "substitutionCount": 0 } }, { "runNode": { "nodeName": "Room1" } }, { "return": { } } ] }, "DoorNode": { "name": "DoorNode", "headers": [ { "key": "title", "value": "DoorNode" } ], "instructions": [ { "pushString": { "value": "key" } }, { "pushFloat": { "value": 1 } }, { "callFunc": { "functionName": "has_item" } }, { "jumpIfFalse": { "destination": 9 } }, { "runCommand": { "commandText": "se door_open", "substitutionCount": 0 } }, { "runCommand": { "commandText": "wait 0.5", "substitutionCount": 0 } }, { "runLine": { "lineID": "line:8e54d35a", "substitutionCount": 0 } }, { "runNode": { "nodeName": "Battle" } }, { "jumpTo": { "destination": 15 } }, { "pop": { } }, { "runCommand": { "commandText": "se locked", "substitutionCount": 0 } }, { "runCommand": { "commandText": "shake 0.3", "substitutionCount": 0 } }, { "runLine": { "lineID": "line:1864d42d", "substitutionCount": 0 } }, { "runNode": { "nodeName": "Room1" } }, { "jumpTo": { "destination": 15 } }, { "return": { } } ] }, "Battle": { "name": "Battle", "headers": [ { "key": "title", "value": "Battle" } ], "instructions": [ { "runCommand": { "commandText": "bg boss fade 0.3", "substitutionCount": 0 } }, { "runCommand": { "commandText": "bgm play battle loop", "substitutionCount": 0 } }, { "runCommand": { "commandText": "sprite show dragon center", "substitutionCount": 0 } }, { "runLine": { "lineID": "line:270243b6", "substitutionCount": 0 } }, { "detourToNode": { "nodeName": "BattleLoop" } }, { "runCommand": { "commandText": "sprite hide dragon", "substitutionCount": 0 } }, { "runCommand": { "commandText": "bgm fade 1.0", "substitutionCount": 0 } }, { "runNode": { "nodeName": "Ending" } }, { "return": { } } ] }, "BattleLoop": { "name": "BattleLoop", "headers": [ { "key": "title", "value": "BattleLoop" } ], "instructions": [ { "pushVariable": { "variableName": "$hp" } }, { "runLine": { "lineID": "line:9cbaa9d8", "substitutionCount": 1 } }, { "pushVariable": { "variableName": "$hp" } }, { "pushFloat": { "value": 25 } }, { "pushFloat": { "value": 2 } }, { "callFunc": { "functionName": "Number.Minus" } }, { "storeVariable": { "variableName": "$hp" } }, { "pop": { } }, { "runCommand": { "commandText": "se hit", "substitutionCount": 0 } }, { "runCommand": { "commandText": "shake 0.4", "substitutionCount": 0 } }, { "pushVariable": { "variableName": "$player_name" } }, { "pushFloat": { "value": 25 } }, { "pushVariable": { "variableName": "$hp" } }, { "runLine": { "lineID": "line:79336eb8", "substitutionCount": 3 } }, { "pushVariable": { "variableName": "$hp" } }, { "pushFloat": { "value": 0 } }, { "pushFloat": { "value": 2 } }, { "callFunc": { "functionName": "Number.LessThanOrEqualTo" } }, { "jumpIfFalse": { "destination": 21 } }, { "runNode": { "nodeName": "GameOver" } }, { "jumpTo": { "destination": 22 } }, { "pop": { } }, { "addOption": { "lineID": "line:ef0369cf", "destination": 28, "substitutionCount": 0, "hasCondition": false } }, { "addOption": { "lineID": "line:f6c704c8", "destination": 40, "substitutionCount": 0, "hasCondition": false } }, { "showOptions": { } }, { "jumpIfFalse": { "destination": 55 } }, { "pop": { } }, { "peekAndJump": { } }, { "pop": { } }, { "pushVariable": { "variableName": "$brave" } }, { "jumpIfFalse": { "destination": 35 } }, { "runLine": { "lineID": "line:55526056", "substitutionCount": 0 } }, { "runLine": { "lineID": "line:c3626721", "substitutionCount": 0 } }, { "return": { } }, { "jumpTo": { "destination": 39 } }, { "pop": { } }, { "runLine": { "lineID": "line:60f703bf", "substitutionCount": 0 } }, { "runNode": { "nodeName": "BattleLoop" } }, { "jumpTo": { "destination": 39 } }, { "jumpTo": { "destination": 55 } }, { "pop": { } }, { "pushVariable": { "variableName": "$hp" } }, { "pushFloat": { "value": 50 } }, { "pushFloat": { "value": 2 } }, { "callFunc": { "functionName": "Number.GreaterThan" } }, { "jumpIfFalse": { "destination": 50 } }, { "runLine": { "lineID": "line:4c960d51", "substitutionCount": 0 } }, { "runCommand": { "commandText": "sprite hide dragon", "substitutionCount": 0 } }, { "runNode": { "nodeName": "Room1" } }, { "jumpTo": { "destination": 54 } }, { "pop": { } }, { "runLine": { "lineID": "line:daa60a26", "substitutionCount": 0 } }, { "runNode": { "nodeName": "BattleLoop" } }, { "jumpTo": { "destination": 54 } }, { "jumpTo": { "destination": 55 } }, { "return": { } } ] }, "MeetKing": { "name": "MeetKing", "headers": [ { "key": "title", "value": "MeetKing" } ], "instructions": [ { "runCommand": { "commandText": "bg dungeon fade 0.3", "substitutionCount": 0 } }, { "runCommand": { "commandText": "bgm play dungeon loop", "substitutionCount": 0 } }, { "runCommand": { "commandText": "sprite show ou center", "substitutionCount": 0 } }, { "pushVariable": { "variableName": "$player_name" } }, { "runLine": { "lineID": "line:7790ef8c", "substitutionCount": 1 } }, { "runLine": { "lineID": "line:e1a0e8fb", "substitutionCount": 0 } }, { "addOption": { "lineID": "line:828e75cd", "destination": 12, "substitutionCount": 0, "hasCondition": false } }, { "addOption": { "lineID": "line:38df7c54", "destination": 17, "substitutionCount": 0, "hasCondition": false } }, { "showOptions": { } }, { "jumpIfFalse": { "destination": 20 } }, { "pop": { } }, { "peekAndJump": { } }, { "pop": { } }, { "runCommand": { "commandText": "save 1", "substitutionCount": 0 } }, { "runLine": { "lineID": "line:14be72ba", "substitutionCount": 0 } }, { "runLine": { "lineID": "line:aeef7b23", "substitutionCount": 0 } }, { "jumpTo": { "destination": 20 } }, { "pop": { } }, { "runLine": { "lineID": "line:9b4a18ca", "substitutionCount": 0 } }, { "jumpTo": { "destination": 20 } }, { "runCommand": { "commandText": "sprite hide ou", "substitutionCount": 0 } }, { "runNode": { "nodeName": "Room1" } }, { "return": { } } ] }, "Ending": { "name": "Ending", "headers": [ { "key": "title", "value": "Ending" } ], "instructions": [ { "runCommand": { "commandText": "bg ending fade 1.0", "substitutionCount": 0 } }, { "runCommand": { "commandText": "bgm play ending loop", "substitutionCount": 0 } }, { "pushVariable": { "variableName": "$player_name" } }, { "runLine": { "lineID": "line:a1ed0e50", "substitutionCount": 1 } }, { "pushVariable": { "variableName": "$brave" } }, { "jumpIfFalse": { "destination": 8 } }, { "runLine": { "lineID": "line:1bbc07c9", "substitutionCount": 0 } }, { "jumpTo": { "destination": 11 } }, { "pop": { } }, { "runLine": { "lineID": "line:8d8c00be", "substitutionCount": 0 } }, { "jumpTo": { "destination": 11 } }, { "runLine": { "lineID": "line:1c91bf2e", "substitutionCount": 0 } }, { "runCommand": { "commandText": "save 1", "substitutionCount": 0 } }, { "runLine": { "lineID": "line:8aa1b859", "substitutionCount": 0 } }, { "runCommand": { "commandText": "wait 0.5", "substitutionCount": 0 } }, { "runCommand": { "commandText": "bgm fade 2.0", "substitutionCount": 0 } }, { "runNode": { "nodeName": "Start" } }, { "return": { } } ] }, "GameOver": { "name": "GameOver", "headers": [ { "key": "title", "value": "GameOver" } ], "instructions": [ { "runCommand": { "commandText": "sprite hide dragon", "substitutionCount": 0 } }, { "runCommand": { "commandText": "bg gameover fade 0.8", "substitutionCount": 0 } }, { "runCommand": { "commandText": "bgm fade 0.5", "substitutionCount": 0 } }, { "runCommand": { "commandText": "se die", "substitutionCount": 0 } }, { "pushVariable": { "variableName": "$player_name" } }, { "runLine": { "lineID": "line:16562138", "substitutionCount": 1 } }, { "runCommand": { "commandText": "wait 1.0", "substitutionCount": 0 } }, { "runLine": { "lineID": "line:8066264f", "substitutionCount": 0 } }, { "runCommand": { "commandText": "phase Start", "substitutionCount": 0 } }, { "stop": { } }, { "return": { } } ] } }, "initialValues": { "$player_name": { "stringValue": "ゆうしゃ" }, "$brave": { "boolValue": false }, "$hp": { "floatValue": 100 }, "$max_hp": { "floatValue": 100 }, "$inv_key": { "boolValue": false }, "$inv_torch": { "boolValue": false }, "$chest_opened": { "boolValue": false }, "$_load_failed": { "boolValue": false }, "$Yarn.Internal.Visiting.Room1": { "floatValue": 0 } }, "languageVersion": 4 }, "strings": { "line:1eeaf1bf": { "text": "タイトル: [color=gold][b]脱出 - 古城の鍵[/b][/color]" }, "line:88daf6c8": { "text": "はじめから" }, "line:328bff51": { "text": "つづきから" }, "line:a4bbf826": { "text": "ナレーション: セーブデータが ありません。" }, "line:eeec70fe": { "text": "おう: ゆうしゃよ、よくぞ もどった。" }, "line:78dc7789": { "text": "おう: なまえを なんとしたかな？" }, "line:c28d7e10": { "text": "アレフ" }, "line:54bd7967": { "text": "ベータ" }, "line:c5a0c6f7": { "text": "おう: そうじゃ、[color=cyan]{0}[/color] じゃったな。" }, "line:5390c180": { "text": "おう: おぬしは ゆうかんか？" }, "line:f794e0ce": { "text": "はい" }, "line:61a4e7b9": { "text": "おう: たのもしいぞ。" }, "line:dbf5ee20": { "text": "いいえ" }, "line:4dc5e957": { "text": "おう: …まあ よかろう。" }, "line:9fa9601e": { "text": "ナレーション: ここは ふるい へやだ。" }, "line:09996769": { "text": "ナレーション: たからばこ と とびら が みえる。" }, "line:b3c86ef0": { "text": "ナレーション: ({0} は はじめて この へやに きた)" }, "line:25f86987": { "text": "ナレーション: (なんども みた こうけい だ)" }, "line:b4e5d617": { "text": "たからばこを しらべる" }, "line:22d5d160": { "text": "とびらを あける" }, "line:453e2032": { "text": "やすむ" }, "line:d30e2745": { "text": "ナレーション: HP が [color=lime]{0}[/color] に かいふくした。" }, "line:695f2edc": { "text": "王に あいに いく" }, "line:d8f0fbf7": { "text": "ナレーション: たからばこは からっぽだ。" }, "line:7b659f69": { "text": "ナレーション: たからばこを あけた！" }, "line:ed55981e": { "text": "ナレーション: [color=yellow]かぎ[/color] を てに いれた。" }, "line:8e54d35a": { "text": "ナレーション: かぎを つかって とびらを あけた！" }, "line:1864d42d": { "text": "ナレーション: かぎが かかっている。" }, "line:270243b6": { "text": "ドラゴン: グルル… よくぞ ここまで きた。" }, "line:9cbaa9d8": { "text": "ドラゴン: HP {0} か。 たえられるかな？" }, "line:79336eb8": { "text": "ナレーション: [color=cyan]{0}[/color] は [color=red]{1}[/color] の ダメージ！ HP は [color=red]{2}[/color] に なった。" }, "line:ef0369cf": { "text": "こうげき" }, "line:55526056": { "text": "ナレーション: ゆうかんに きりつけた！ [color=red][b]クリティカル！[/b][/color]" }, "line:c3626721": { "text": "ドラゴン: グ… やられた…" }, "line:60f703bf": { "text": "ナレーション: おそるおそる きりつけた。" }, "line:f6c704c8": { "text": "にげる" }, "line:4c960d51": { "text": "ナレーション: たいりょく が ある うちに にげきった。" }, "line:daa60a26": { "text": "ナレーション: にげきれない！" }, "line:7790ef8c": { "text": "おう: おお、{0}よ。" }, "line:e1a0e8fb": { "text": "おう: たびの きろくを のこすか？" }, "line:828e75cd": { "text": "セーブする" }, "line:14be72ba": { "text": "ナレーション: (セーブしました)" }, "line:aeef7b23": { "text": "おう: きを つけて いくのじゃ。" }, "line:38df7c54": { "text": "やめておく" }, "line:9b4a18ca": { "text": "おう: …よかろう。" }, "line:a1ed0e50": { "text": "おう: よくぞ もどった、{0}。" }, "line:1bbc07c9": { "text": "おう: そなた こそ しんの ゆうしゃ じゃ。" }, "line:8d8c00be": { "text": "おう: ぶじで なによりじゃ。" }, "line:1c91bf2e": { "text": "おう: たびの きろくを のこそう。" }, "line:8aa1b859": { "text": "ナレーション: (セーブしました)" }, "line:16562138": { "text": "ナレーション: [color=cyan]{0}[/color] は たおれた。" }, "line:8066264f": { "text": "ナレーション: [color=red][b]GAME OVER[/b][/color]" } }, "diagnostics": [ ] }